azure/mgmt/attestation/__init__.py
azure/mgmt/attestation/_attestation_management_client.py
azure/mgmt/attestation/_configuration.py
azure/mgmt/attestation/_version.py
azure/mgmt/attestation/aio/__init__.py
azure/mgmt/attestation/aio/_attestation_management_client.py
azure/mgmt/attestation/aio/_configuration.py
azure/mgmt/attestation/aio/operations/__init__.py
azure/mgmt/attestation/aio/operations/_attestation_providers_operations.py
azure/mgmt/attestation/aio/operations/_operations.py
azure/mgmt/attestation/models/__init__.py
azure/mgmt/attestation/models/_attestation_management_client_enums.py
azure/mgmt/attestation/models/_models.py
azure/mgmt/attestation/models/_models_py3.py
azure/mgmt/attestation/operations/__init__.py
azure/mgmt/attestation/operations/_attestation_providers_operations.py
azure/mgmt/attestation/operations/_operations.py
azure_mgmt_attestation-1.0.0.dist-info/METADATA
azure_mgmt_attestation-1.0.0.dist-info/WHEEL
azure_mgmt_attestation-1.0.0.dist-info/top_level.txt
azure_mgmt_attestation-1.0.0.dist-info/RECORD
